weft/__init__.py
weft/__main__.py
weft/cli.py
weft/describe_graph.py
weft/mcp_server.py
weft/server.py
weft/export/__init__.py
weft/export/browser.py
weft/export/cache.py
weft/export/crawl.py
weft/export/graph.py
weft/export/llm.py
weft/export/obsidian.py
weft/export/similarity.py
weft/tui/__init__.py
weft/tui/app.py
weft/utils/__init__.py
weft/utils/text.py
weft/utils/url.py
weft_graph-1.2.0.dist-info/METADATA
weft_graph-1.2.0.dist-info/WHEEL
weft_graph-1.2.0.dist-info/entry_points.txt
weft_graph-1.2.0.dist-info/top_level.txt
weft_graph-1.2.0.dist-info/RECORD
