Metadata-Version: 2.4
Name: weft-graph
Version: 1.2.0
Summary: A local-first knowledge graph for your browsing - Chrome extension + CLI
Author: Avi Solanki
License: MIT
Project-URL: Homepage, https://github.com/Avi-141/weft
Project-URL: Repository, https://github.com/Avi-141/weft
Keywords: knowledge-graph,browsing,chrome-extension,browser,tabs,llm,clustering,tui,semantic-search,local-first,second-brain,navigation-tracking
Classifier: Development Status :: 4 - Beta
Classifier: Environment :: Console
Classifier: Intended Audience :: End Users/Desktop
Classifier: License :: OSI Approved :: MIT License
Classifier: Operating System :: MacOS
Classifier: Operating System :: Microsoft :: Windows
Classifier: Programming Language :: Python :: 3
Classifier: Programming Language :: Python :: 3.9
Classifier: Programming Language :: Python :: 3.10
Classifier: Programming Language :: Python :: 3.11
Classifier: Programming Language :: Python :: 3.12
Classifier: Topic :: Utilities
Requires-Python: >=3.9
Requires-Dist: requests
Requires-Dist: trafilatura
Requires-Dist: rich
Requires-Dist: textual
Requires-Dist: fastmcp
Requires-Dist: uvicorn
Requires-Dist: fastapi
Provides-Extra: firefox
Requires-Dist: lz4; extra == "firefox"
Provides-Extra: js
Requires-Dist: playwright; extra == "js"
